{
	"configurations" : 
	[
		{
			"directories" : 
			[
				{
					"build" : ".",
					"jsonFile" : "directory-.-Debug-d0094a50bb2071803777.json",
					"minimumCMakeVersion" : 
					{
						"string" : "3.28"
					},
					"projectIndex" : 0,
					"source" : ".",
					"targetIndexes" : 
					[
						0
					]
				}
			],
			"name" : "Debug",
			"projects" : 
			[
				{
					"directoryIndexes" : 
					[
						0
					],
					"name" : "15649",
					"targetIndexes" : 
					[
						0
					]
				}
			],
			"targets" : 
			[
				{
					"directoryIndex" : 0,
					"id" : "15649::@6890427a1f51a3e7e1df",
					"jsonFile" : "target-15649-Debug-e7b9de763b24456a75ee.json",
					"name" : "15649",
					"projectIndex" : 0
				}
			]
		}
	],
	"kind" : "codemodel",
	"paths" : 
	{
		"build" : "C:/Users/gowon/baekjoon/backtracking/15649/cmake-build-debug",
		"source" : "C:/Users/gowon/baekjoon/backtracking/15649"
	},
	"version" : 
	{
		"major" : 2,
		"minor" : 6
	}
}
